{
  "Norms": [
    {
      "act": "ГК",
      "date": "26.01.1996",
      "number": "146-ФЗ",
      "art": "785",
      "art_prilozhenie": "",
      "art_chast": "",
      "art_punkt": "1",
      "art_podpunkt": "",
      "art_abzats": "",
      "scope": "общий",
      "gen_note": "Определяет договор перевозки груза как соглашение, по которому перевозчик обязуется доставить вверенный ему отправителем груз в пункт назначения и выдать его управомоченному лицу.",
      "case_note": "Норма устанавливает правовые основания договорных отношений между отправителем груза и транспортной компанией, что подтверждает наличие обязательства по доставке."
    },
    {
      "act": "ГК",
      "date": "26.01.1996",
      "number": "146-ФЗ",
      "art": "792",
      "art_prilozhenie": "",
      "art_chast": "",
      "art_punkt": "",
      "art_podpunkt": "",
      "art_abzats": "",
      "scope": "общий",
      "gen_note": "Устанавливает обязанность перевозчика доставить груз в пункт назначения в сроки, определенные транспортными уставами, кодексами или договором перевозки.",
      "case_note": "Норма применима к ситуации просрочки доставки груза, так как дата доставки 22.04.2024 не была соблюдена транспортной компанией."
    },
    {
      "act": "ГК",
      "date": "26.01.1996",
      "number": "146-ФЗ",
      "art": "796",
      "art_prilozhenie": "",
      "art_chast": "",
      "art_punkt": "1",
      "art_podpunkt": "",
      "art_abzats": "",
      "scope": "специальный",
      "gen_note": "Устанавливает ответственность перевозчика за несохранность груза, происшедшую после принятия его к перевозке и до выдачи грузополучателю, если перевозчик не докажет отсутствие своей вины.",
      "case_note": "Норма непосредственно регулирует ответственность транспортной компании за утрату груза, который был принят 15.03.2024 и не доставлен получателю."
    },
    {
      "act": "ГК",
      "date": "26.01.1996",
      "number": "146-ФЗ",
      "art": "796",
      "art_prilozhenie": "",
      "art_chast": "",
      "art_punkt": "2",
      "art_podpunkt": "",
      "art_abzats": "",
      "scope": "специальный",
      "gen_note": "Определяет размер возмещения ущерба при утрате груза: в размере объявленной стоимости, если груз сдан к перевозке с объявлением его ценности.",
      "case_note": "Норма применима, так как отправка была с объявленной стоимостью, что позволяет требовать возмещение в размере объявленной стоимости груза."
    },
    {
      "act": "ГК",
      "date": "26.01.1996",
      "number": "146-ФЗ",
      "art": "797",
      "art_prilozhenie": "",
      "art_chast": "",
      "art_punkt": "1",
      "art_podpunkt": "",
      "art_abzats": "",
      "scope": "специальный",
      "gen_note": "Устанавливает обязательный досудебный претензионный порядок: до предъявления иска к перевозчику обязательно предъявление ему претензии в порядке, предусмотренном транспортными уставами.",
      "case_note": "Норма подтверждает правомерность направления претензии 30.05.2024 как обязательного этапа перед обращением в суд."
    },
    {
      "act": "ГК",
      "date": "26.01.1996",
      "number": "146-ФЗ",
      "art": "797",
      "art_prilozhenie": "",
      "art_chast": "",
      "art_punkt": "2",
      "art_podpunkt": "",
      "art_abzats": "",
      "scope": "специальный",
      "gen_note": "Определяет право грузоотправителя или грузополучателя предъявить иск к перевозчику в случае полного или частичного отказа удовлетворить претензию либо неполучения ответа в установленный срок.",
      "case_note": "Норма даёт основание для обращения в суд, так как транспортная компания перестала отвечать на обращения и не предоставила своевременный ответ на претензию."
    },
    {
      "act": "Устав автомобильного транспорта и городского наземного электрического транспорта",
      "date": "08.11.2007",
      "number": "259-ФЗ",
      "art": "40",
      "art_prilozhenie": "",
      "art_chast": "1",
      "art_punkt": "",
      "art_podpunkt": "",
      "art_abzats": "",
      "scope": "специальный",
      "gen_note": "Устанавливает обязанность перевозчиков рассмотреть предъявленные претензии и уведомить заявителей о результатах рассмотрения в письменной форме в течение 30 дней со дня получения претензии.",
      "case_note": "Норма определяет срок ответа на претензию (30 дней), который истёк, так как претензия направлена 30.05.2024, а ответ не получен в установленный срок."
    },
    {
      "act": "Устав автомобильного транспорта и городского наземного электрического транспорта",
      "date": "08.11.2007",
      "number": "259-ФЗ",
      "art": "42",
      "art_prilozhenie": "",
      "art_chast": "1",
      "art_punkt": "",
      "art_podpunkt": "",
      "art_abzats": "",
      "scope": "специальный",
      "gen_note": "Устанавливает срок исковой давности по требованиям, вытекающим из договоров перевозок, в один год со дня, определяемого в соответствии с транспортными уставами.",
      "case_note": "Норма определяет срок для обращения в суд (1 год), который необходимо соблюсти для защиты прав по договору перевозки груза."
    },
    {
      "act": "ГК",
      "date": "30.11.1994",
      "number": "51-ФЗ",
      "art": "393",
      "art_prilozhenie": "",
      "art_chast": "",
      "art_punkt": "1",
      "art_podpunkt": "",
      "art_abzats": "",
      "scope": "общий",
      "gen_note": "Устанавливает общую обязанность должника возместить кредитору убытки, причиненные неисполнением или ненадлежащим исполнением обязательства.",
      "case_note": "Норма обосновывает право требовать возмещения убытков от транспортной компании за неисполнение обязательства по доставке груза."
    },
    {
      "act": "ГК",
      "date": "30.11.1994",
      "number": "51-ФЗ",
      "art": "395",
      "art_prilozhenie": "",
      "art_chast": "",
      "art_punkt": "1",
      "art_podpunkt": "",
      "art_abzats": "",
      "scope": "общий",
      "gen_note": "Предусматривает ответственность за неисполнение денежного обязательства в виде уплаты процентов за пользование чужими денежными средствами.",
      "case_note": "Норма позволяет требовать проценты на сумму возмещения за период просрочки выплаты после установления обязанности перевозчика возместить стоимость груза."
    }
  ],
  "Conclusion": {
    "synthesis": "Основания ответственности. По договору перевозки груза перевозчик обязан доставить вверенный ему груз в пункт назначения и выдать его управомоченному лицу (п. 1 ст. 785 ГК РФ) . Перевозчик несет ответственность за несохранность груза, происшедшую после принятия его к перевозке и до выдачи грузополучателю, если не докажет отсутствие своей вины (п. 1 ст. 796 ГК РФ) . Вина перевозчика презюмируется, бремя доказывания отсутствия вины лежит на перевозчике .\n\nПоследствия утраты груза. При утрате груза, сданного к перевозке с объявлением его ценности, ущерб возмещается в размере объявленной стоимости груза (п. 2 ст. 796 ГК РФ) . Также возможно взыскание убытков по ст. 393 ГК РФ  и процентов за пользование чужими денежными средствами по ст. 395 ГК РФ при просрочке выплаты возмещения .\n\nПроцедура защиты прав. До предъявления иска к перевозчику обязательно соблюдение досудебного претензионного порядка (п. 1 ст. 797 ГК РФ) . Претензия должна быть рассмотрена перевозчиком в течение 30 дней со дня получения (ч. 1 ст. 40 УАТ) . Иск может быть предъявлен при отказе удовлетворить претензию или неполучении ответа в установленный срок (п. 2 ст. 797 ГК РФ) . Срок исковой давности составляет 1 год (ст. 42 УАТ) .\n\nЗащитные механизмы. При задержке ответа на претензию более 30 дней право на иск возникает автоматически. Судебная практика подтверждает, что перевозчик не может уклоняться от ответственности путём затягивания ответов и переноса сроков .",
    "answer": "Возможно при условии. Вы имеете право требовать возмещения стоимости груза в размере объявленной стоимости на основании п. 2 ст. 796 ГК РФ , так как груз был сдан с объявленной стоимостью. Претензионный порядок соблюдён (претензия направлена 30.05.2024), срок ответа 30 дней истёк (ч. 1 ст. 40 УАТ) . Можно обращаться в суд на основании п. 2 ст. 797 ГК РФ . Необходимо учитывать срок исковой давности 1 год (ст. 42 УАТ) . Для окончательной проверки требуется: копия договора перевозки, документ об объявленной стоимости, подтверждение направления и получения претензии, документы о стоимости груза.",
    "algo": "Шаг 1. Подготовить документы: договор перевозки, транспортную накладную, документ об объявленной стоимости груза, подтверждение оплаты услуг перевозки, копию претензии от 30.05.2024 с доказательством направления (почтовая квитанция, опись вложения) .\n\nШаг 2. Дождаться истечения 30-дневного срока на ответ на претензию (ч. 1 ст. 40 УАТ) . Если ответ не получен или получен отказ — готовить иск. Срок считается с даты получения претензии перевозчиком.\n\nШаг 3. Подготовить исковое заявление: указать требования о взыскании объявленной стоимости груза (п. 2 ст. 796 ГК РФ) , процентов за пользование чужими денежными средствами (ст. 395 ГК РФ) , судебных расходов. Определить подсудность: арбитражный суд (если стороны — юрлица/ИП) или суд общей юрисдикции (если отправитель — физлицо-потребитель).\n\nШаг 4. Подать иск в суд в пределах срока исковой давности 1 год (ст. 42 УАТ) . Срок исчисляется с момента, когда груз должен был быть доставлен (22.04.2024) или с даты получения ответа на претензию.\n\nШаг 5. Участвовать в судебных заседаниях, представлять доказательства утраты груза (переписка с менеджерами, информация об утере). Вина перевозчика презюмируется (п. 1 ст. 796 ГК РФ) , перевозчик должен доказать отсутствие вины.\n\nШаг 6. После вступления решения в силу получить исполнительный лист и предъявить его к взысканию. При неисполнении — обратиться к судебным приставам."
  }
}