{
  "Norms": [
    {
      "act": "ГК",
      "date": "30.11.1994",
      "number": "51-ФЗ",
      "art": "244",
      "art_prilozhenie": "",
      "art_chast": "1",
      "art_punkt": "",
      "art_podpunkt": "",
      "art_abzats": "",
      "scope": "общий",
      "gen_note": "Определяет понятие долевой собственности как имущество, находящееся в собственности двух или более лиц с определением доли каждого.",
      "case_note": "Применима к ситуации, так как квартира после раздела имущества находится в долевой собственности бывших супругов по 1/2 доле."
    },
    {
      "act": "ГК",
      "date": "30.11.1994",
      "number": "51-ФЗ",
      "art": "247",
      "art_prilozhenie": "",
      "art_chast": "1",
      "art_punkt": "",
      "art_podpunkt": "",
      "art_abzats": "",
      "scope": "общий",
      "gen_note": "Регулирует порядок владения и пользования имуществом, находящимся в долевой собственности, по соглашению всех участников или через суд.",
      "case_note": "Применима, так как бывший супруг отказывается согласовать порядок пользования квартирой, что требует судебного определения."
    },
    {
      "act": "ГК",
      "date": "30.11.1994",
      "number": "51-ФЗ",
      "art": "247",
      "art_prilozhenie": "",
      "art_chast": "2",
      "art_punkt": "",
      "art_podpunkt": "",
      "art_abzats": "",
      "scope": "общий",
      "gen_note": "Устанавливает право участника долевой собственности на компенсацию при невозможности предоставления ему части имущества в натуре.",
      "case_note": "Прямо относится к требованию о взыскании компенсации за использование доли истца бывшим супругом."
    },
    {
      "act": "ГК",
      "date": "30.11.1994",
      "number": "51-ФЗ",
      "art": "30",
      "art_prilozhenie": "",
      "art_chast": "1",
      "art_punkt": "",
      "art_podpunkt": "",
      "art_abzats": "",
      "scope": "общий",
      "gen_note": "Закрепляет права собственника владеть, пользоваться и распоряжаться своим имуществом.",
      "case_note": "Подтверждает право пользовательницы как сособственника на пользование своей долей квартиры."
    },
    {
      "act": "ЖК",
      "date": "29.12.2004",
      "number": "188-ФЗ",
      "art": "30",
      "art_prilozhenie": "",
      "art_chast": "1",
      "art_punkt": "",
      "art_podpunkt": "",
      "art_abzats": "",
      "scope": "специальный",
      "gen_note": "Определяет права и обязанности собственника жилого помещения, включая право пользования помещением.",
      "case_note": "Специальная норма для жилых помещений, подтверждает права пользовательницы на пользование квартирой как собственником доли."
    },
    {
      "act": "ЖК",
      "date": "29.12.2004",
      "number": "188-ФЗ",
      "art": "31",
      "art_prilozhenie": "",
      "art_chast": "1",
      "art_punkt": "",
      "art_podpunkt": "",
      "art_abzats": "",
      "scope": "специальный",
      "gen_note": "Регулирует права и обязанности граждан, проживающих совместно с собственником жилого помещения.",
      "case_note": "Относится к ситуации с пропиской новой супруги и ребёнка бывшего мужа в спорной квартире."
    },
    {
      "act": "СК",
      "date": "29.12.1995",
      "number": "223-ФЗ",
      "art": "38",
      "art_prilozhenie": "",
      "art_chast": "1",
      "art_punkt": "",
      "art_podpunkt": "",
      "art_abzats": "",
      "scope": "специальный",
      "gen_note": "Регулирует раздел общего имущества супругов и определение долей каждого из супругов.",
      "case_note": "Применима к уже завершённому разделу имущества, в результате которого определены доли по 1/2."
    },
    {
      "act": "ГПК",
      "date": "14.11.2002",
      "number": "138-ФЗ",
      "art": "131",
      "art_prilozhenie": "",
      "art_chast": "1",
      "art_punkt": "",
      "art_podpunkt": "",
      "art_abzats": "",
      "scope": "общий",
      "gen_note": "Определяет форму и содержание искового заявления для обращения в суд.",
      "case_note": "Необходима для правильного оформления иска о взыскании компенсации и определении порядка пользования."
    },
    {
      "act": "ГПК",
      "date": "14.11.2002",
      "number": "138-ФЗ",
      "art": "132",
      "art_prilozhenie": "",
      "art_chast": "1",
      "art_punkt": "",
      "art_podpunkt": "",
      "art_abzats": "",
      "scope": "общий",
      "gen_note": "Устанавливает перечень документов, прилагаемых к исковому заявлению.",
      "case_note": "Определяет необходимые документы для подачи иска (документы на квартиру, решение о разделе, доказательства)."
    },
    {
      "act": "ГПК",
      "date": "14.11.2002",
      "number": "138-ФЗ",
      "art": "28",
      "art_prilozhenie": "",
      "art_chast": "1",
      "art_punkt": "",
      "art_podpunkt": "",
      "art_abzats": "",
      "scope": "общий",
      "gen_note": "Определяет общую подсудность исков по месту жительства ответчика.",
      "case_note": "Указывает, в какой суд подавать иск — по месту жительства бывшего супруга (место нахождения квартиры)."
    }
  ],
  "Conclusion": {
    "synthesis": "Основания: После раздела имущества квартира находится в долевой собственности бывших супругов по 1/2 доле каждому (ГК РФ ст. 244, СК РФ ст. 38). Как сособственник, пользовательница имеет право владеть, пользоваться и распоряжаться своей долей (ГК РФ ст. 30, ЖК РФ ст. 30). Последствия: Владение и пользование имуществом в долевой собственности осуществляется по соглашению всех участников, а при недостижении согласия — в порядке, устанавливаемом судом (ГК РФ ст. 247 ч. 1). При невозможности предоставления доли в натуре или фактическом недопуске к пользованию, участник долевой собственности вправе требовать компенсацию за несоразмерное использование его доли другими сособственниками (ГК РФ ст. 247 ч. 2). Процедуры: Для защиты прав необходимо обратиться в районный суд по месту нахождения квартиры (ГПК РФ ст. 28) с исковым заявлением (ГПК РФ ст. 131) и приложением документов (ГПК РФ ст. 132). Защита: Судебная практика (Постановление Пленума ВС РФ № 10, Определение ВС РФ) подтверждает право на компенсацию при фактическом недопуске сособственника к пользованию имуществом. Размер компенсации определяется исходя из рыночной стоимости аренды аналогичного помещения, пропорционально доле истца. Дополнительно можно требовать определения порядка пользования квартирой или выдела доли в натуре (если технически возможно).",
    "answer": "Возможно при условии обращения в суд. Вы вправе взыскать компенсацию за использование вашей доли бывшим супругом на основании ГК РФ ст. 247 ч. 2, а также определить порядок пользования квартирой через суд (ГК РФ ст. 247 ч. 1, ЖК РФ ст. 30). Ключевые тезисы: 1) Долевая собственность подтверждена решением суда о разделе имущества; 2) Отказ бывшего супруга предоставить доступ к квартире нарушает ваши права сособственника; 3) Компенсация рассчитывается пропорционально вашей доле (1/2) от рыночной стоимости аренды; 4) Прописка новых жильцов без вашего согласия может быть оспорена, если их вселение нарушает ваши права.",
    "algo": "Шаг 1: Сбор документов — решение суда о разделе имущества, выписка из ЕГРН о долевой собственности, доказательства отказа в доступе (переписка, свидетели), доказательства угроз (скриншоты мессенджеров). Ссылки: ГПК РФ ст. 132. Шаг 2: Оценка размера компенсации — заказать отчёт об оценке рыночной стоимости аренды аналогичного жилья в вашем регионе для расчёта суммы иска (1/2 от стоимости аренды за период недопуска). Шаг 3: Досудебная претензия — направить бывшему супругу письменное требование о предоставлении доступа к квартире или выплате компенсации заказным письмом с уведомлением (срок ответа 30 дней). Ссылки: ГК РФ ст. 247. Шаг 4: Подготовка искового заявления — указать требования: 1) взыскание компенсации за пользование долей; 2) определение порядка пользования квартирой; 3) обязание передать ключи. Ссылки: ГПК РФ ст. 131, ГК РФ ст. 247. Шаг 5: Подача иска в районный суд — по месту нахождения квартиры (месту жительства ответчика). Уплатить госпошлину (рассчитывается от суммы имущественных требований). Ссылки: ГПК РФ ст. 28. Шаг 6: Участие в судебных заседаниях — представить все доказательства, ходатайствовать о вызове свидетелей при необходимости. Шаг 7: Исполнение решения — после вступления решения в силу получить исполнительный лист и передать приставам для принудительного исполнения (передача ключей, взыскание компенсации)."
  }
}