{
  "Norms": [
    {
      "act": "ГК РФ",
      "date": "30.11.1994",
      "number": "51-ФЗ",
      "art": "23",
      "art_prilozhenie": "",
      "art_chast": "1",
      "art_punkt": "",
      "art_podpunkt": "",
      "art_abzats": "",
      "scope": "общий",
      "gen_note": "Устанавливает право гражданина заниматься предпринимательской деятельностью без образования юридического лица с момента государственной регистрации в качестве индивидуального предпринимателя.",
      "case_note": "Норма определяет правовое основание для получения статуса ИП и момент возникновения права на предпринимательскую деятельность."
    },
    {
      "act": "ГК РФ",
      "date": "30.11.1994",
      "number": "51-ФЗ",
      "art": "23",
      "art_prilozhenie": "",
      "art_chast": "3",
      "art_punkt": "",
      "art_podpunkt": "",
      "art_abzats": "",
      "scope": "общий",
      "gen_note": "Регулирует условия, при которых гражданин может заниматься предпринимательской деятельностью без регистрации, и последствия такой деятельности.",
      "case_note": "Норма важна для понимания необходимости обязательной регистрации для легальной предпринимательской деятельности."
    },
    {
      "act": "Федеральный закон «О государственной регистрации юридических лиц и индивидуальных предпринимателей»",
      "date": "08.08.2001",
      "number": "129-ФЗ",
      "art": "22.1",
      "art_prilozhenie": "",
      "art_chast": "1",
      "art_punkt": "",
      "art_podpunkt": "",
      "art_abzats": "",
      "scope": "специальный",
      "gen_note": "Определяет перечень документов, представляемых в регистрирующий орган при государственной регистрации физического лица в качестве индивидуального предпринимателя.",
      "case_note": "Норма непосредственно регулирует процедуру регистрации ИП и устанавливает требования к пакету документов."
    },
    {
      "act": "Федеральный закон «О государственной регистрации юридических лиц и индивидуальных предпринимателей»",
      "date": "08.08.2001",
      "number": "129-ФЗ",
      "art": "22.1",
      "art_prilozhenie": "",
      "art_chast": "1",
      "art_punkt": "а",
      "art_podpunkt": "",
      "art_abzats": "",
      "scope": "специальный",
      "gen_note": "Требует представления подписанного заявителем заявления по установленной форме для регистрации ИП.",
      "case_note": "Определяет необходимость заполнения заявления по форме Р21001 как основного документа для регистрации."
    },
    {
      "act": "Федеральный закон «О государственной регистрации юридических лиц и индивидуальных предпринимателей»",
      "date": "08.08.2001",
      "number": "129-ФЗ",
      "art": "22.1",
      "art_prilozhenie": "",
      "art_chast": "1",
      "art_punkt": "б",
      "art_podpunkt": "",
      "art_abzats": "",
      "scope": "специальный",
      "gen_note": "Требует копии всех страниц документа, удостоверяющего личность физического лица, регистрируемого в качестве ИП.",
      "case_note": "Устанавливает требование к документу, удостоверяющему личность заявителя."
    },
    {
      "act": "Федеральный закон «О государственной регистрации юридических лиц и индивидуальных предпринимателей»",
      "date": "08.08.2001",
      "number": "129-ФЗ",
      "art": "8",
      "art_prilozhenie": "",
      "art_chast": "1",
      "art_punkt": "",
      "art_podpunkt": "",
      "art_abzats": "",
      "scope": "специальный",
      "gen_note": "Устанавливает срок государственной регистрации — не более чем три рабочих дня с момента представления документов в регистрирующий орган.",
      "case_note": "Определяет временные рамки процедуры регистрации, что важно для планирования заявителем."
    },
    {
      "act": "Федеральный закон «О государственной регистрации юридических лиц и индивидуальных предпринимателей»",
      "date": "08.08.2001",
      "number": "129-ФЗ",
      "art": "11",
      "art_prilozhenie": "",
      "art_chast": "1",
      "art_punkt": "",
      "art_podpunkt": "",
      "art_abzats": "",
      "scope": "специальный",
      "gen_note": "Регулирует принятие решения о государственной регистрации и внесение записи в соответствующий государственный реестр.",
      "case_note": "Определяет юридический факт завершения процедуры регистрации и возникновения статуса ИП."
    },
    {
      "act": "НК РФ",
      "date": "05.08.2000",
      "number": "117-ФЗ",
      "art": "333.33",
      "art_prilozhenie": "",
      "art_chast": "1",
      "art_punkt": "",
      "art_podpunkt": "3",
      "art_abzats": "",
      "scope": "специальный",
      "gen_note": "Устанавливает размер государственной пошлины за государственную регистрацию физического лица в качестве индивидуального предпринимателя.",
      "case_note": "Определяет финансовое обязательство заявителя при регистрации ИП — 800 рублей."
    },
    {
      "act": "НК РФ",
      "date": "05.08.2000",
      "number": "117-ФЗ",
      "art": "333.35",
      "art_prilozhenie": "",
      "art_chast": "1",
      "art_punkt": "",
      "art_podpunkt": "",
      "art_abzats": "",
      "scope": "специальный",
      "gen_note": "Предусматривает освобождение от уплаты государственной пошлины при направлении документов в электронном виде.",
      "case_note": "Позволяет заявителю сэкономить на госпошлине при использовании электронных способов подачи документов."
    },
    {
      "act": "Приказ Федеральной налоговой службы",
      "date": "31.08.2020",
      "number": "ЕД-7-14/617@",
      "art": "",
      "art_prilozhenie": "13",
      "art_chast": "",
      "art_punkt": "",
      "art_podpunkt": "",
      "art_abzats": "",
      "scope": "специальный",
      "gen_note": "Утверждает форму заявления о государственной регистрации физического лица в качестве индивидуального предпринимателя (форма Р21001, КНД 1112501).",
      "case_note": "Определяет обязательную форму заявления для регистрации ИП, действующую в 2025-2026 годах."
    }
  ],
  "Conclusion": {
    "synthesis": "Регистрация физического лица в качестве индивидуального предпринимателя регулируется специальным законодательством о государственной регистрации. Правовое основание закреплено в статье 23 ГК РФ, которая предоставляет гражданину право заниматься предпринимательской деятельностью без образования юридического лица с момента государственной регистрации . Процедура регистрации детально регламентирована Федеральным законом № 129-ФЗ: статья 22.1 определяет перечень необходимых документов, статья 8 устанавливает срок регистрации (не более трёх рабочих дней), статья 11 регулирует принятие решения о регистрации . Финансовый аспект регулируется Налоговым кодексом: статья 333.33 устанавливает размер госпошлины в 800 рублей, однако статья 333.35 предусматривает освобождение от уплаты при электронной подаче документов . Форма заявления утверждена Приказом ФНС № ЕД-7-14/617@ (форма Р21001) . Согласно разъяснениям ФНС и судебной практике, отказ в регистрации возможен только по основаниям, прямо предусмотренным законом (неполный пакет документов, недостоверные сведения, наличие запрета на предпринимательскую деятельность). Для окончательной проверки актуальности норм рекомендуется свериться с официальными источниками (КонсультантПлюс, Гарант, официальный сайт ФНС), так как законодательство может изменяться.",
    "answer": "Да, регистрация физического лица в качестве индивидуального предпринимателя возможна при соблюдении установленных требований. Ключевые условия: достижение совершеннолетия (или эмансипация/брак для несовершеннолетних), отсутствие запрета на предпринимательскую деятельность, представление полного пакета документов в регистрирующий орган (ФНС). Госпошлина составляет 800 рублей, но не уплачивается при электронной подаче документов (ст. 333.35 НК РФ) . Срок регистрации — не более трёх рабочих дней (ст. 8 ФЗ-129) .",
    "algo": "Шаг 1: Подготовить пакет документов — заявление по форме Р21001 (Приказ ФНС № ЕД-7-14/617@), копию всех страниц паспорта, квитанцию об уплате госпошлины (если подаётся в бумажной форме) . Шаг 2: Выбрать способ подачи документов — лично в налоговую инспекцию, через МФЦ, по почте или в электронном виде через сайт ФНС/Госуслуги (электронная подача освобождает от госпошлины) . Шаг 3: Подать документы в регистрирующий орган (ФНС по месту жительства) . Шаг 4: Ожидать решения в срок не более трёх рабочих дней (ст. 8 ФЗ-129) . Шаг 5: Получить документы о регистрации — лист записи ЕГРИП и свидетельство о постановке на налоговый учёт (ст. 11 ФЗ-129) . Шаг 6: При необходимости — выбрать систему налогообложения (можно подать уведомление одновременно с регистрацией или в течение 30 дней) . Для минимизации рисков отказа рекомендуется проверить достоверность сведений в заявлении и убедиться в отсутствии ограничений на предпринимательскую деятельность (Письмо ФНС от 2023 г., судебная практика по ст. 23 ГК РФ)."
  }
}